[
  {
    "id": "P08-D38-1481",
    "part": 8,
    "part_name_ko": "정치·사회",
    "part_name_zh": "政治・社會",
    "day": 38,
    "word_no": 1481,
    "word": "흠치다",
    "pos_ko": "",
    "pos_zh": "",
    "pos_short": "",
    "meaning_zh": "",
    "example_ko": "",
    "example_zh": "",
    "tags": "Part8,Day38",
    "is_overview_word": true
  },
  {
    "id": "P08-D38-1482",
    "part": 8,
    "part_name_ko": "정치·사회",
    "part_name_zh": "政治・社會",
    "day": 38,
    "word_no": 1482,
    "word": "정면",
    "pos_ko": "",
    "pos_zh": "",
    "pos_short": "",
    "meaning_zh": "",
    "example_ko": "",
    "example_zh": "",
    "tags": "Part8,Day38",
    "is_overview_word": true
  },
  {
    "id": "P08-D38-1483",
    "part": 8,
    "part_name_ko": "정치·사회",
    "part_name_zh": "政治・社會",
    "day": 38,
    "word_no": 1483,
    "word": "출산",
    "pos_ko": "",
    "pos_zh": "",
    "pos_short": "",
    "meaning_zh": "",
    "example_ko": "",
    "example_zh": "",
    "tags": "Part8,Day38",
    "is_overview_word": true
  },
  {
    "id": "P08-D38-1484",
    "part": 8,
    "part_name_ko": "정치·사회",
    "part_name_zh": "政治・社會",
    "day": 38,
    "word_no": 1484,
    "word": "지겹다",
    "pos_ko": "",
    "pos_zh": "",
    "pos_short": "",
    "meaning_zh": "",
    "example_ko": "",
    "example_zh": "",
    "tags": "Part8,Day38",
    "is_overview_word": true
  },
  {
    "id": "P08-D38-1485",
    "part": 8,
    "part_name_ko": "정치·사회",
    "part_name_zh": "政治・社會",
    "day": 38,
    "word_no": 1485,
    "word": "출근길",
    "pos_ko": "",
    "pos_zh": "",
    "pos_short": "",
    "meaning_zh": "",
    "example_ko": "",
    "example_zh": "",
    "tags": "Part8,Day38",
    "is_overview_word": true
  },
  {
    "id": "P08-D38-1486",
    "part": 8,
    "part_name_ko": "정치·사회",
    "part_name_zh": "政治・社會",
    "day": 38,
    "word_no": 1486,
    "word": "악취",
    "pos_ko": "",
    "pos_zh": "",
    "pos_short": "",
    "meaning_zh": "",
    "example_ko": "",
    "example_zh": "",
    "tags": "Part8,Day38",
    "is_overview_word": true
  },
  {
    "id": "P08-D38-1487",
    "part": 8,
    "part_name_ko": "정치·사회",
    "part_name_zh": "政治・社會",
    "day": 38,
    "word_no": 1487,
    "word": "취재",
    "pos_ko": "",
    "pos_zh": "",
    "pos_short": "",
    "meaning_zh": "",
    "example_ko": "",
    "example_zh": "",
    "tags": "Part8,Day38",
    "is_overview_word": true
  },
  {
    "id": "P08-D38-1488",
    "part": 8,
    "part_name_ko": "정치·사회",
    "part_name_zh": "政治・社會",
    "day": 38,
    "word_no": 1488,
    "word": "안내판",
    "pos_ko": "",
    "pos_zh": "",
    "pos_short": "",
    "meaning_zh": "",
    "example_ko": "",
    "example_zh": "",
    "tags": "Part8,Day38",
    "is_overview_word": true
  },
  {
    "id": "P08-D38-1489",
    "part": 8,
    "part_name_ko": "정치·사회",
    "part_name_zh": "政治・社會",
    "day": 38,
    "word_no": 1489,
    "word": "처수",
    "pos_ko": "",
    "pos_zh": "",
    "pos_short": "",
    "meaning_zh": "",
    "example_ko": "",
    "example_zh": "",
    "tags": "Part8,Day38",
    "is_overview_word": true
  },
  {
    "id": "P08-D38-1490",
    "part": 8,
    "part_name_ko": "정치·사회",
    "part_name_zh": "政治・社會",
    "day": 38,
    "word_no": 1490,
    "word": "안부",
    "pos_ko": "",
    "pos_zh": "",
    "pos_short": "",
    "meaning_zh": "",
    "example_ko": "",
    "example_zh": "",
    "tags": "Part8,Day38",
    "is_overview_word": true
  },
  {
    "id": "P08-D38-1491",
    "part": 8,
    "part_name_ko": "정치·사회",
    "part_name_zh": "政治・社會",
    "day": 38,
    "word_no": 1491,
    "word": "안방",
    "pos_ko": "",
    "pos_zh": "",
    "pos_short": "",
    "meaning_zh": "",
    "example_ko": "",
    "example_zh": "",
    "tags": "Part8,Day38",
    "is_overview_word": true
  },
  {
    "id": "P08-D38-1492",
    "part": 8,
    "part_name_ko": "정치·사회",
    "part_name_zh": "政治・社會",
    "day": 38,
    "word_no": 1492,
    "word": "휴대",
    "pos_ko": "",
    "pos_zh": "",
    "pos_short": "",
    "meaning_zh": "",
    "example_ko": "",
    "example_zh": "",
    "tags": "Part8,Day38",
    "is_overview_word": true
  },
  {
    "id": "P08-D38-1493",
    "part": 8,
    "part_name_ko": "정치·사회",
    "part_name_zh": "政治・社會",
    "day": 38,
    "word_no": 1493,
    "word": "가로등",
    "pos_ko": "",
    "pos_zh": "",
    "pos_short": "",
    "meaning_zh": "",
    "example_ko": "",
    "example_zh": "",
    "tags": "Part8,Day38",
    "is_overview_word": true
  },
  {
    "id": "P08-D38-1494",
    "part": 8,
    "part_name_ko": "정치·사회",
    "part_name_zh": "政治・社會",
    "day": 38,
    "word_no": 1494,
    "word": "오로지",
    "pos_ko": "",
    "pos_zh": "",
    "pos_short": "",
    "meaning_zh": "",
    "example_ko": "",
    "example_zh": "",
    "tags": "Part8,Day38",
    "is_overview_word": true
  },
  {
    "id": "P08-D38-1495",
    "part": 8,
    "part_name_ko": "정치·사회",
    "part_name_zh": "政治・社會",
    "day": 38,
    "word_no": 1495,
    "word": "진지하다",
    "pos_ko": "",
    "pos_zh": "",
    "pos_short": "",
    "meaning_zh": "",
    "example_ko": "",
    "example_zh": "",
    "tags": "Part8,Day38",
    "is_overview_word": true
  },
  {
    "id": "P08-D38-1496",
    "part": 8,
    "part_name_ko": "정치·사회",
    "part_name_zh": "政治・社會",
    "day": 38,
    "word_no": 1496,
    "word": "차마",
    "pos_ko": "",
    "pos_zh": "",
    "pos_short": "",
    "meaning_zh": "",
    "example_ko": "",
    "example_zh": "",
    "tags": "Part8,Day38",
    "is_overview_word": true
  },
  {
    "id": "P08-D38-1497",
    "part": 8,
    "part_name_ko": "정치·사회",
    "part_name_zh": "政治・社會",
    "day": 38,
    "word_no": 1497,
    "word": "출국",
    "pos_ko": "",
    "pos_zh": "",
    "pos_short": "",
    "meaning_zh": "",
    "example_ko": "",
    "example_zh": "",
    "tags": "Part8,Day38",
    "is_overview_word": true
  },
  {
    "id": "P08-D38-1498",
    "part": 8,
    "part_name_ko": "정치·사회",
    "part_name_zh": "政治・社會",
    "day": 38,
    "word_no": 1498,
    "word": "치다",
    "pos_ko": "",
    "pos_zh": "",
    "pos_short": "",
    "meaning_zh": "",
    "example_ko": "",
    "example_zh": "",
    "tags": "Part8,Day38",
    "is_overview_word": true
  },
  {
    "id": "P08-D38-1499",
    "part": 8,
    "part_name_ko": "정치·사회",
    "part_name_zh": "政治・社會",
    "day": 38,
    "word_no": 1499,
    "word": "군대",
    "pos_ko": "",
    "pos_zh": "",
    "pos_short": "",
    "meaning_zh": "",
    "example_ko": "",
    "example_zh": "",
    "tags": "Part8,Day38",
    "is_overview_word": true
  },
  {
    "id": "P08-D38-1500",
    "part": 8,
    "part_name_ko": "정치·사회",
    "part_name_zh": "政治・社會",
    "day": 38,
    "word_no": 1500,
    "word": "웹지",
    "pos_ko": "",
    "pos_zh": "",
    "pos_short": "",
    "meaning_zh": "",
    "example_ko": "",
    "example_zh": "",
    "tags": "Part8,Day38",
    "is_overview_word": true
  },
  {
    "id": "P08-D38-1501",
    "part": 8,
    "part_name_ko": "정치·사회",
    "part_name_zh": "政治・社會",
    "day": 38,
    "word_no": 1501,
    "word": "언론",
    "pos_ko": "",
    "pos_zh": "",
    "pos_short": "",
    "meaning_zh": "",
    "example_ko": "",
    "example_zh": "",
    "tags": "Part8,Day38",
    "is_overview_word": true
  },
  {
    "id": "P08-D38-1502",
    "part": 8,
    "part_name_ko": "정치·사회",
    "part_name_zh": "政治・社會",
    "day": 38,
    "word_no": 1502,
    "word": "가로막다",
    "pos_ko": "",
    "pos_zh": "",
    "pos_short": "",
    "meaning_zh": "",
    "example_ko": "",
    "example_zh": "",
    "tags": "Part8,Day38",
    "is_overview_word": true
  },
  {
    "id": "P08-D38-1503",
    "part": 8,
    "part_name_ko": "정치·사회",
    "part_name_zh": "政治・社會",
    "day": 38,
    "word_no": 1503,
    "word": "온",
    "pos_ko": "",
    "pos_zh": "",
    "pos_short": "",
    "meaning_zh": "",
    "example_ko": "",
    "example_zh": "",
    "tags": "Part8,Day38",
    "is_overview_word": true
  },
  {
    "id": "P08-D38-1504",
    "part": 8,
    "part_name_ko": "정치·사회",
    "part_name_zh": "政治・社會",
    "day": 38,
    "word_no": 1504,
    "word": "진실",
    "pos_ko": "",
    "pos_zh": "",
    "pos_short": "",
    "meaning_zh": "",
    "example_ko": "",
    "example_zh": "",
    "tags": "Part8,Day38",
    "is_overview_word": true
  },
  {
    "id": "P08-D38-1505",
    "part": 8,
    "part_name_ko": "정치·사회",
    "part_name_zh": "政治・社會",
    "day": 38,
    "word_no": 1505,
    "word": "측",
    "pos_ko": "",
    "pos_zh": "",
    "pos_short": "",
    "meaning_zh": "",
    "example_ko": "",
    "example_zh": "",
    "tags": "Part8,Day38",
    "is_overview_word": true
  },
  {
    "id": "P08-D38-1506",
    "part": 8,
    "part_name_ko": "정치·사회",
    "part_name_zh": "政治・社會",
    "day": 38,
    "word_no": 1506,
    "word": "야경",
    "pos_ko": "",
    "pos_zh": "",
    "pos_short": "",
    "meaning_zh": "",
    "example_ko": "",
    "example_zh": "",
    "tags": "Part8,Day38",
    "is_overview_word": true
  },
  {
    "id": "P08-D38-1507",
    "part": 8,
    "part_name_ko": "정치·사회",
    "part_name_zh": "政治・社會",
    "day": 38,
    "word_no": 1507,
    "word": "치르다동사",
    "pos_ko": "",
    "pos_zh": "",
    "pos_short": "",
    "meaning_zh": "",
    "example_ko": "",
    "example_zh": "",
    "tags": "Part8,Day38",
    "is_overview_word": true
  },
  {
    "id": "P08-D38-1508",
    "part": 8,
    "part_name_ko": "정치·사회",
    "part_name_zh": "政治・社會",
    "day": 38,
    "word_no": 1508,
    "word": "심지어",
    "pos_ko": "",
    "pos_zh": "",
    "pos_short": "",
    "meaning_zh": "",
    "example_ko": "",
    "example_zh": "",
    "tags": "Part8,Day38",
    "is_overview_word": true
  },
  {
    "id": "P08-D38-1510",
    "part": 8,
    "part_name_ko": "정치·사회",
    "part_name_zh": "政治・社會",
    "day": 38,
    "word_no": 1510,
    "word": "영",
    "pos_ko": "",
    "pos_zh": "",
    "pos_short": "",
    "meaning_zh": "",
    "example_ko": "",
    "example_zh": "",
    "tags": "Part8,Day38",
    "is_overview_word": true
  },
  {
    "id": "P08-D38-1511",
    "part": 8,
    "part_name_ko": "정치·사회",
    "part_name_zh": "政治・社會",
    "day": 38,
    "word_no": 1511,
    "word": "가루",
    "pos_ko": "",
    "pos_zh": "",
    "pos_short": "",
    "meaning_zh": "",
    "example_ko": "",
    "example_zh": "",
    "tags": "Part8,Day38",
    "is_overview_word": true
  },
  {
    "id": "P08-D38-1512",
    "part": 8,
    "part_name_ko": "정치·사회",
    "part_name_zh": "政治・社會",
    "day": 38,
    "word_no": 1512,
    "word": "올라타다",
    "pos_ko": "",
    "pos_zh": "",
    "pos_short": "",
    "meaning_zh": "",
    "example_ko": "",
    "example_zh": "",
    "tags": "Part8,Day38",
    "is_overview_word": true
  },
  {
    "id": "P08-D38-1513",
    "part": 8,
    "part_name_ko": "정치·사회",
    "part_name_zh": "政治・社會",
    "day": 38,
    "word_no": 1513,
    "word": "올려놓다",
    "pos_ko": "",
    "pos_zh": "",
    "pos_short": "",
    "meaning_zh": "",
    "example_ko": "",
    "example_zh": "",
    "tags": "Part8,Day38",
    "is_overview_word": true
  },
  {
    "id": "P08-D38-1514",
    "part": 8,
    "part_name_ko": "정치·사회",
    "part_name_zh": "政治・社會",
    "day": 38,
    "word_no": 1514,
    "word": "심판",
    "pos_ko": "",
    "pos_zh": "",
    "pos_short": "",
    "meaning_zh": "",
    "example_ko": "",
    "example_zh": "",
    "tags": "Part8,Day38",
    "is_overview_word": true
  },
  {
    "id": "P08-D38-1515",
    "part": 8,
    "part_name_ko": "정치·사회",
    "part_name_zh": "政治・社會",
    "day": 38,
    "word_no": 1515,
    "word": "야근",
    "pos_ko": "",
    "pos_zh": "",
    "pos_short": "",
    "meaning_zh": "",
    "example_ko": "",
    "example_zh": "",
    "tags": "Part8,Day38",
    "is_overview_word": true
  },
  {
    "id": "P08-D38-1516",
    "part": 8,
    "part_name_ko": "정치·사회",
    "part_name_zh": "政治・社會",
    "day": 38,
    "word_no": 1516,
    "word": "여간",
    "pos_ko": "",
    "pos_zh": "",
    "pos_short": "",
    "meaning_zh": "",
    "example_ko": "",
    "example_zh": "",
    "tags": "Part8,Day38",
    "is_overview_word": true
  },
  {
    "id": "P08-D38-1517",
    "part": 8,
    "part_name_ko": "정치·사회",
    "part_name_zh": "政治・社會",
    "day": 38,
    "word_no": 1517,
    "word": "엿보다",
    "pos_ko": "",
    "pos_zh": "",
    "pos_short": "",
    "meaning_zh": "",
    "example_ko": "",
    "example_zh": "",
    "tags": "Part8,Day38",
    "is_overview_word": true
  },
  {
    "id": "P08-D38-1518",
    "part": 8,
    "part_name_ko": "정치·사회",
    "part_name_zh": "政治・社會",
    "day": 38,
    "word_no": 1518,
    "word": "실례",
    "pos_ko": "",
    "pos_zh": "",
    "pos_short": "",
    "meaning_zh": "",
    "example_ko": "",
    "example_zh": "",
    "tags": "Part8,Day38",
    "is_overview_word": true
  },
  {
    "id": "P08-D38-1520",
    "part": 8,
    "part_name_ko": "정치·사회",
    "part_name_zh": "政治・社會",
    "day": 38,
    "word_no": 1520,
    "word": "승진하다",
    "pos_ko": "",
    "pos_zh": "",
    "pos_short": "",
    "meaning_zh": "",
    "example_ko": "",
    "example_zh": "",
    "tags": "Part8,Day38",
    "is_overview_word": true
  }
]